jupyterlab_athena_analytics/__init__.py
jupyterlab_athena_analytics/_version.py
jupyterlab_athena_analytics-0.5.17.data/data/share/jupyter/labextensions/jupyterlab_athena_analytics/package.json
jupyterlab_athena_analytics-0.5.17.data/data/share/jupyter/labextensions/jupyterlab_athena_analytics/static/509.1866d2287dc3dd54b397.js
jupyterlab_athena_analytics-0.5.17.data/data/share/jupyter/labextensions/jupyterlab_athena_analytics/static/728.c9fba78fc7d4a52b2765.js
jupyterlab_athena_analytics-0.5.17.data/data/share/jupyter/labextensions/jupyterlab_athena_analytics/static/remoteEntry.6897030c3ef7f0bc60a2.js
jupyterlab_athena_analytics-0.5.17.data/data/share/jupyter/labextensions/jupyterlab_athena_analytics/static/style.js
jupyterlab_athena_analytics-0.5.17.data/data/share/jupyter/labextensions/jupyterlab_athena_analytics/static/third-party-licenses.json
jupyterlab_athena_analytics-0.5.17.data/data/share/jupyter/labextensions/jupyterlab_athena_analytics/install.json
jupyterlab_athena_analytics-0.5.17.dist-info/METADATA
jupyterlab_athena_analytics-0.5.17.dist-info/WHEEL
jupyterlab_athena_analytics-0.5.17.dist-info/licenses/LICENSE
jupyterlab_athena_analytics-0.5.17.dist-info/RECORD
