Metadata-Version: 2.3
Name: jupyterlab_athena_analytics
Version: 0.5.17
Summary: A JupyterLab extension.
Project-URL: Homepage, https://github.com/github_username/jupyterlab_athena_analytics
Project-URL: Bug Tracker, https://github.com/github_username/jupyterlab_athena_analytics/issues
Project-URL: Repository, https://github.com/github_username/jupyterlab_athena_analytics.git
Author-email: Athena Intelligence <team@athenaintelligence.ai>
License: BSD 3-Clause License
License-File: LICENSE
Classifier: Framework :: Jupyter
Classifier: Framework :: Jupyter :: JupyterLab
Classifier: Framework :: Jupyter :: JupyterLab :: 4
Classifier: Framework :: Jupyter :: JupyterLab :: Extensions
Classifier: Framework :: Jupyter :: JupyterLab :: Extensions :: Prebuilt
Classifier: License :: OSI Approved :: BSD License
Classifier: Programming Language :: Python
Classifier: Programming Language :: Python :: 3
Classifier: Programming Language :: Python :: 3.8
Classifier: Programming Language :: Python :: 3.9
Classifier: Programming Language :: Python :: 3.10
Classifier: Programming Language :: Python :: 3.11
Requires-Python: >=3.8
